ejabberdctl
