Metadata-Version: 1.1
Name: ejabberdctl.py
Version: 0.2
Summary: Python client for Ejabberd XML-RPC Administration API
Home-page: https://gitlab.com/markuz/ejabberdctl.py
Author: Marek Kuziel
Author-email: marek@kuziel.nz
License: MIT
Keywords: ejabberd xmlrpc administration api
Platform: UNKNOWN
Classifier: Development Status :: 5 - Production/Stable
Classifier: Environment :: Console
Classifier: Intended Audience :: Developers
Classifier: License :: OSI Approved :: MIT License
Classifier: Operating System :: OS Independent
Classifier: Programming Language :: Python
Classifier: Topic :: Communications
